revar/__init__.py
revar-0.3.dist-info/LICENSE
revar-0.3.dist-info/METADATA
revar-0.3.dist-info/WHEEL
revar-0.3.dist-info/top_level.txt
revar-0.3.dist-info/RECORD
