Metadata-Version: 2.1
Name: revar
Version: 0.3
Summary: Replace specific values ​​with custom variables
Home-page: https://github.com/decave27/revar
Author: decave27
Author-email: decave27@gmail.com
License: MIT
Project-URL: Source, https://github.com/decave27/revar
Project-URL: Tracker, https://github.com/decave27/revar/issues
Keywords: replace,custom,variable
Platform: UNKNOWN
Classifier: Environment :: Console
Classifier: Programming Language :: Python :: 3.7
Classifier: Programming Language :: Python :: 3.8
Classifier: Programming Language :: Python :: Implementation
Classifier: Programming Language :: Python :: Implementation :: CPython
Requires-Python: >=3.7
